lib_roa_checker/__init__.py
lib_roa_checker/roa.py
lib_roa_checker/roa_checker.py
lib_roa_checker/roa_trie.py
lib_roa_checker/roa_tries.py
lib_roa_checker/roa_validity.py
lib_roa_checker/tests/__init__.py
lib_roa_checker/tests/test_roa_checker.py
lib_roa_checker-0.0.1.dist-info/AUTHORS
lib_roa_checker-0.0.1.dist-info/LICENSE
lib_roa_checker-0.0.1.dist-info/METADATA
lib_roa_checker-0.0.1.dist-info/WHEEL
lib_roa_checker-0.0.1.dist-info/top_level.txt
lib_roa_checker-0.0.1.dist-info/RECORD
