Metadata-Version: 2.1
Name: lib-roa-checker
Version: 0.0.1
Summary: Creates a trie of ROAs for fast lookups
Home-page: https://github.com/jfuruness/lib_roa_checker.git
Author: Justin Furuness
Author-email: jfuruness@gmail.com
License: BSD
Keywords: Furuness,prefix,cidr,inet,trie,cidr-trie,roas,roas-trie,ROA,ROAs,ROAs-trie
Platform: UNKNOWN
Classifier: Environment :: Console
Classifier: Intended Audience :: Developers
Classifier: License :: OSI Approved :: BSD License
Classifier: Operating System :: POSIX :: Linux
Classifier: Programming Language :: Python :: 3
Requires-Python: >=3.8
Requires-Dist: ip-address
Requires-Dist: lib-cidr-trie
Requires-Dist: pytest
